driver/__init__.py
driver/command.py
driver/core.py
driver_downloader-0.2.0.dist-info/entry_points.txt
driver_downloader-0.2.0.dist-info/license.txt
driver_downloader-0.2.0.dist-info/WHEEL
driver_downloader-0.2.0.dist-info/METADATA
driver_downloader-0.2.0.dist-info/RECORD
