Metadata-Version: 2.1
Name: driver-downloader
Version: 0.2.0
Summary: chromedriver downloader
Home-page: https://github.com/modaye/driver
License: MIT
Keywords: selenium,chromedriver
Author: Tai
Author-email: flywacool@gmail.com
Maintainer: Tai Hui
Maintainer-email: flywacool@gmail.com
Requires-Python: >=3.10,<4.0
Classifier: License :: OSI Approved :: MIT License
Classifier: Programming Language :: Python :: 3
Classifier: Programming Language :: Python :: 3.10
Classifier: Topic :: Software Development :: Libraries :: Python Modules
Requires-Dist: httpx (>=0.23.2,<0.24.0)
Requires-Dist: typer (>=0.7.0,<0.8.0)
Project-URL: Repository, https://github.com/modaye/driver
